Lab2_ClockBy3/ClockBy3.v
// ClockBy3.v

module ClockBy3(clk, reset, clk_out);
    input clk;      // 50MHz clock input
    input reset;    // Active high reset
    output clk_out; // 16.66MHz clock output
    
    // 2-bit registers for counting 0, 1, 2
    reg [1:0] pos_count, neg_count;
    
    // Output is high when either counter reaches 2
    assign clk_out = ((pos_count == 2) | (neg_count == 2));
    
    // Positive edge counter
    always @(posedge clk)
        if (reset)
            pos_count <= 0; // Reset counter
        else if (pos_count == 2) 
            pos_count <= 0; // Reset after reaching 2
        else 
            pos_count <= pos_count + 1; // Increment counter
            
    // Negative edge counter
    always @(negedge clk)
        if (reset)
            neg_count <= 0; // Reset counter
        else if (neg_count == 2) 
            neg_count <= 0; // Reset after reaching 2
        else 
            neg_count <= neg_count + 1; // Increment counter
endmodule

Lab2_ClockBy3/clkdiv3_tb.v
// clkdiv3_tb.v

`timescale 1ns/100ps // Define time unit and precision
module clkdiv3_tb;
    reg clk, reset;
    wire clk_out;

    // Instantiate the DUT
    ClockBy3 INST (clk, reset, clk_out);

    // Initialize clock
    initial clk = 1'b0;
    
    // Generate clock: period = 10 time units
    always #5 clk = ~clk;

    // Test sequence
    initial begin
        #5 reset = 1'b1;  // Apply reset
        #10 reset = 1'b0; // Release reset
        #500 $finish;     // Run for 500 time units then end
    end

    // Monitor and dump signals for waveform viewer
    initial begin
        $monitor("clk = %b, reset = %b, clk_out = %b", clk, reset, clk_out);
        $dumpfile("clkdiv3_tb.vcd"); // Output VCD file
        $dumpvars(0, clkdiv3_tb);    // Dump all variables
    end
endmodule

Lab2_ClockBy3/simulation/questa/clkdiv3_tb.vcd
$date
	Thu May 21 07:39:06 2026
$end
$version
	Questa Intel Starter FPGA Edition Version 2021.2
$end
$timescale
	1ps
$end

$scope module clkdiv3_tb $end
$var reg 1 ! clk $end
$var reg 1 " reset $end
$var wire 1 # clk_out $end

$scope module INST $end
$var wire 1 $ clk $end
$var wire 1 % reset $end
$var wire 1 # clk_out $end
$var reg 2 & pos_count [1:0] $end
$var reg 2 ' neg_count [1:0] $end
$upscope $end
$upscope $end
$enddefinitions $end
#0
$dumpvars
0!
x"
bx &
bx '
x#
x%
0$
$end
#5000
1!
1"
1%
1$
b0 &
#10000
0!
0$
b0 '
0#
#15000
0"
1!
0%
1$
b1 &
#20000
0!
0$
b1 '
#25000
1!
1$
b10 &
1#
#30000
0!
0$
b10 '
#35000
1!
1$
b0 &
#40000
0!
0$
b0 '
0#
#45000
1!
1$
b1 &
#50000
0!
0$
b1 '
#55000
1!
1$
b10 &
1#
#60000
0!
0$
b10 '
#65000
1!
1$
b0 &
#70000
0!
0$
b0 '
0#
#75000
1!
1$
b1 &
#80000
0!
0$
b1 '
#85000
1!
1$
b10 &
1#
#90000
0!
0$
b10 '
#95000
1!
1$
b0 &
#100000
0!
0$
b0 '
0#
#105000
1!
1$
b1 &
#110000
0!
0$
b1 '
#115000
1!
1$
b10 &
1#
#120000
0!
0$
b10 '
#125000
1!
1$
b0 &
#130000
0!
0$
b0 '
0#
#135000
1!
1$
b1 &
#140000
0!
0$
b1 '
#145000
1!
1$
b10 &
1#
#150000
0!
0$
b10 '
#155000
1!
1$
b0 &
#160000
0!
0$
b0 '
0#
#165000
1!
1$
b1 &
#170000
0!
0$
b1 '
#175000
1!
1$
b10 &
1#
#180000
0!
0$
b10 '
#185000
1!
1$
b0 &
#190000
0!
0$
b0 '
0#
#195000
1!
1$
b1 &
#200000
0!
0$
b1 '
#205000
1!
1$
b10 &
1#
#210000
0!
0$
b10 '
#215000
1!
1$
b0 &
#220000
0!
0$
b0 '
0#
#225000
1!
1$
b1 &
#230000
0!
0$
b1 '
#235000
1!
1$
b10 &
1#
#240000
0!
0$
b10 '
#245000
1!
1$
b0 &
#250000
0!
0$
b0 '
0#
#255000
1!
1$
b1 &
#260000
0!
0$
b1 '
#265000
1!
1$
b10 &
1#
#270000
0!
0$
b10 '
#275000
1!
1$
b0 &
#280000
0!
0$
b0 '
0#
#285000
1!
1$
b1 &
#290000
0!
0$
b1 '
#295000
1!
1$
b10 &
1#
#300000
0!
0$
b10 '
#305000
1!
1$
b0 &
#310000
0!
0$
b0 '
0#
#315000
1!
1$
b1 &
#320000
0!
0$
b1 '
#325000
1!
1$
b10 &
1#
#330000
0!
0$
b10 '
#335000
1!
1$
b0 &
#340000
0!
0$
b0 '
0#
#345000
1!
1$
b1 &
#350000
0!
0$
b1 '
#355000
1!
1$
b10 &
1#
#360000
0!
0$
b10 '
#365000
1!
1$
b0 &
#370000
0!
0$
b0 '
0#
#375000
1!
1$
b1 &
#380000
0!
0$
b1 '
#385000
1!
1$
b10 &
1#
#390000
0!
0$
b10 '
#395000
1!
1$
b0 &
#400000
0!
0$
b0 '
0#
#405000
1!
1$
b1 &
#410000
0!
0$
b1 '
#415000
1!
1$
b10 &
1#
#420000
0!
0$
b10 '
#425000
1!
1$
b0 &
#430000
0!
0$
b0 '
0#
#435000
1!
1$
b1 &
#440000
0!
0$
b1 '
#445000
1!
1$
b10 &
1#
#450000
0!
0$
b10 '
#455000
1!
1$
b0 &
#460000
0!
0$
b0 '
0#
#465000
1!
1$
b1 &
#470000
0!
0$
b1 '
#475000
1!
1$
b10 &
1#
#480000
0!
0$
b10 '
#485000
1!
1$
b0 &
#490000
0!
0$
b0 '
0#
#495000
1!
1$
b1 &
#500000
0!
0$
b1 '
#505000
1!
1$
b10 &
1#
#510000
0!
0$
b10 '
